MANIFEST.in
README
setup.py
jsonapp/__init__.py
jsonapp/client.js
jsonapp/client.py
jsonapp/jsonapp.py
jsonapp/redirector.py
jsonapp/router.py
jsonapp/server.py
jsonapp/staticapp.py
jsonapp/webapp.py
jsonapp.egg-info/PKG-INFO
jsonapp.egg-info/SOURCES.txt
jsonapp.egg-info/dependency_links.txt
jsonapp.egg-info/top_level.txt