Metadata-Version: 1.0
Name: jsonapp
Version: 0.0.2
Summary: A simple framework for pure-ajax applications.
Home-page: https://github.com/thinxer/jsonapp
Author: Jianfei Wang
Author-email: me@thinxer.com
License: MIT
Keywords: json wsgi webapp
Platform: UNKNOWN
